tv_api_work/__init__.py
tv_api_work/tv_api_work.py
tv_logger_conf/__init__.py
tv_logger_conf/tv_logger_conf.py
tv_qt_class/__init__.py
tv_qt_class/tv_qt_class.py
tv_sqllite/__init__.py
tv_sqllite/tv_sqllite.py
tv_viewer/__init__.py
tv_viewer/tv_viewer.py
tv_viewer-2.3.data/scripts/tv_viewer.py
tv_viewer-2.3.dist-info/LICENSE.md
tv_viewer-2.3.dist-info/METADATA
tv_viewer-2.3.dist-info/WHEEL
tv_viewer-2.3.dist-info/top_level.txt
tv_viewer-2.3.dist-info/RECORD
